{"/":{"title":"🦉 Biiraiverse Wiki","content":"\nWelcome to the **Biiraiverse**.\n\nExplore some of the languages:\n\n- [[notes/Lenethailef|Lenethailef]]","lastmodified":"2022-08-07T01:39:05.531716875Z","tags":null},"/notes/Continent-E":{"title":"Continent E","content":"\nstub","lastmodified":"2022-08-07T01:39:05.531716875Z","tags":null},"/notes/Lenethailef":{"title":"Lenethailef","content":"\n**Lenethailef** is a [[notes/Qal languages|Qal language]] spoken in the southwestern coastal regions of [[notes/Continent E|Continent E]]. It emerged as a distinct language around 1100 BP.\n","lastmodified":"2022-08-07T01:39:05.531716875Z","tags":null},"/notes/Qal-languages":{"title":"Continent E","content":"\nstub","lastmodified":"2022-08-07T01:39:05.531716875Z","tags":null}}